{
  "components": {
    "schemas": {
      "ErrorBody": {
        "properties": {
          "code": {
            "type": "string"
          },
          "error": {
            "type": "string"
          },
          "request_id": {
            "type": "string"
          }
        },
        "required": [
          "error"
        ],
        "type": "object"
      },
      "HealthBody": {
        "properties": {
          "status": {
            "type": "string"
          }
        },
        "required": [
          "status"
        ],
        "type": "object"
      },
      "HealthEnvelope": {
        "properties": {
          "data": {
            "$ref": "#/components/schemas/HealthBody"
          },
          "request_id": {
            "type": "string"
          }
        },
        "required": [
          "data"
        ],
        "type": "object"
      },
      "LoginResponse": {
        "properties": {
          "token": {
            "type": "string"
          },
          "user": {
            "$ref": "#/components/schemas/UserResponse"
          }
        },
        "type": "object"
      },
      "MonitorResponse": {
        "properties": {
          "alert_enabled": {
            "type": "boolean"
          },
          "id": {
            "format": "int64",
            "type": "integer"
          },
          "name": {
            "type": "string"
          },
          "poll_interval_minutes": {
            "type": "integer"
          },
          "query_text": {
            "type": "string"
          },
          "status": {
            "type": "string"
          },
          "user_id": {
            "format": "int64",
            "type": "integer"
          }
        },
        "type": "object"
      },
      "NotificationResponse": {
        "properties": {
          "channel": {
            "type": "string"
          },
          "created_at": {
            "format": "date-time",
            "type": "string"
          },
          "delivery_status": {
            "type": "string"
          },
          "id": {
            "format": "int64",
            "type": "integer"
          }
        },
        "type": "object"
      },
      "UserResponse": {
        "properties": {
          "display_name": {
            "type": "string"
          },
          "email": {
            "type": "string"
          },
          "id": {
            "format": "int64",
            "type": "integer"
          }
        },
        "type": "object"
      }
    },
    "securitySchemes": {
      "bearer": {
        "bearerFormat": "JWT",
        "scheme": "bearer",
        "type": "http"
      }
    }
  },
  "info": {
    "description": "X (Twitter) hot-topic monitoring platform API",
    "title": "HotKey Server",
    "version": "1.0.0"
  },
  "openapi": "3.1.0",
  "paths": {
    "/api/v1/auth/login": {
      "post": {
        "operationId": "login",
        "responses": {
          "200": {
            "content": {
              "application/json": {}
            },
            "description": "OK"
          },
          "default": {
            "content": {
              "application/json": {
                "schema": {
                  "$ref": "#/components/schemas/ErrorBody"
                }
              }
            },
            "description": "Error"
          }
        },
        "summary": "Login with email and password",
        "tags": [
          "auth"
        ]
      }
    },
    "/api/v1/auth/register": {
      "post": {
        "operationId": "register",
        "responses": {
          "200": {
            "content": {
              "application/json": {}
            },
            "description": "OK"
          },
          "default": {
            "content": {
              "application/json": {
                "schema": {
                  "$ref": "#/components/schemas/ErrorBody"
                }
              }
            },
            "description": "Error"
          }
        },
        "summary": "Register a new user",
        "tags": [
          "auth"
        ]
      }
    },
    "/api/v1/monitors": {
      "get": {
        "operationId": "list-monitors",
        "responses": {
          "200": {
            "content": {
              "application/json": {}
            },
            "description": "OK"
          },
          "default": {
            "content": {
              "application/json": {
                "schema": {
                  "$ref": "#/components/schemas/ErrorBody"
                }
              }
            },
            "description": "Error"
          }
        },
        "security": [
          {
            "bearer": []
          }
        ],
        "summary": "List monitors",
        "tags": [
          "monitors"
        ]
      },
      "post": {
        "operationId": "create-monitor",
        "responses": {
          "200": {
            "content": {
              "application/json": {}
            },
            "description": "OK"
          },
          "default": {
            "content": {
              "application/json": {
                "schema": {
                  "$ref": "#/components/schemas/ErrorBody"
                }
              }
            },
            "description": "Error"
          }
        },
        "security": [
          {
            "bearer": []
          }
        ],
        "summary": "Create a monitor",
        "tags": [
          "monitors"
        ]
      }
    },
    "/api/v1/monitors/{id}": {
      "get": {
        "operationId": "get-monitor",
        "responses": {
          "200": {
            "content": {
              "application/json": {}
            },
            "description": "OK"
          },
          "default": {
            "content": {
              "application/json": {
                "schema": {
                  "$ref": "#/components/schemas/ErrorBody"
                }
              }
            },
            "description": "Error"
          }
        },
        "security": [
          {
            "bearer": []
          }
        ],
        "summary": "Get a monitor",
        "tags": [
          "monitors"
        ]
      },
      "patch": {
        "operationId": "update-monitor",
        "responses": {
          "200": {
            "content": {
              "application/json": {}
            },
            "description": "OK"
          },
          "default": {
            "content": {
              "application/json": {
                "schema": {
                  "$ref": "#/components/schemas/ErrorBody"
                }
              }
            },
            "description": "Error"
          }
        },
        "security": [
          {
            "bearer": []
          }
        ],
        "summary": "Update a monitor",
        "tags": [
          "monitors"
        ]
      }
    },
    "/api/v1/monitors/{id}/posts": {
      "get": {
        "operationId": "list-posts",
        "responses": {
          "200": {
            "content": {
              "application/json": {}
            },
            "description": "OK"
          },
          "default": {
            "content": {
              "application/json": {
                "schema": {
                  "$ref": "#/components/schemas/ErrorBody"
                }
              }
            },
            "description": "Error"
          }
        },
        "security": [
          {
            "bearer": []
          }
        ],
        "summary": "List posts for a monitor",
        "tags": [
          "content"
        ]
      }
    },
    "/api/v1/monitors/{id}/topics": {
      "get": {
        "operationId": "list-topics",
        "responses": {
          "200": {
            "content": {
              "application/json": {}
            },
            "description": "OK"
          },
          "default": {
            "content": {
              "application/json": {
                "schema": {
                  "$ref": "#/components/schemas/ErrorBody"
                }
              }
            },
            "description": "Error"
          }
        },
        "security": [
          {
            "bearer": []
          }
        ],
        "summary": "List topics for a monitor",
        "tags": [
          "topics"
        ]
      }
    },
    "/api/v1/monitors/{id}/trends": {
      "get": {
        "operationId": "get-monitor-trends",
        "responses": {
          "200": {
            "content": {
              "application/json": {}
            },
            "description": "OK"
          },
          "default": {
            "content": {
              "application/json": {
                "schema": {
                  "$ref": "#/components/schemas/ErrorBody"
                }
              }
            },
            "description": "Error"
          }
        },
        "security": [
          {
            "bearer": []
          }
        ],
        "summary": "Get trends for a monitor",
        "tags": [
          "trends"
        ]
      }
    },
    "/api/v1/notifications": {
      "get": {
        "operationId": "list-notifications",
        "responses": {
          "200": {
            "content": {
              "application/json": {}
            },
            "description": "OK"
          },
          "default": {
            "content": {
              "application/json": {
                "schema": {
                  "$ref": "#/components/schemas/ErrorBody"
                }
              }
            },
            "description": "Error"
          }
        },
        "security": [
          {
            "bearer": []
          }
        ],
        "summary": "List unread notifications",
        "tags": [
          "notifications"
        ]
      }
    },
    "/api/v1/notifications/{id}/read": {
      "post": {
        "operationId": "mark-notification-read",
        "responses": {
          "200": {
            "content": {
              "application/json": {}
            },
            "description": "OK"
          },
          "default": {
            "content": {
              "application/json": {
                "schema": {
                  "$ref": "#/components/schemas/ErrorBody"
                }
              }
            },
            "description": "Error"
          }
        },
        "security": [
          {
            "bearer": []
          }
        ],
        "summary": "Mark notification as read",
        "tags": [
          "notifications"
        ]
      }
    },
    "/api/v1/topics/{id}/trends": {
      "get": {
        "operationId": "get-topic-trends",
        "responses": {
          "200": {
            "content": {
              "application/json": {}
            },
            "description": "OK"
          },
          "default": {
            "content": {
              "application/json": {
                "schema": {
                  "$ref": "#/components/schemas/ErrorBody"
                }
              }
            },
            "description": "Error"
          }
        },
        "security": [
          {
            "bearer": []
          }
        ],
        "summary": "Get trends for a topic",
        "tags": [
          "trends"
        ]
      }
    },
    "/healthz": {
      "get": {
        "operationId": "health-check",
        "responses": {
          "200": {
            "content": {
              "application/json": {
                "schema": {
                  "$ref": "#/components/schemas/HealthEnvelope"
                }
              }
            },
            "description": "OK"
          },
          "default": {
            "content": {
              "application/json": {
                "schema": {
                  "$ref": "#/components/schemas/ErrorBody"
                }
              }
            },
            "description": "Error"
          }
        },
        "summary": "Health check",
        "tags": [
          "health"
        ]
      }
    }
  }
}